gel/__init__.py
gel/gelcd.py
gel/gelfista.py
gel/gelpaths.py
gel/ridgepaths.py
torchgel-2.0.0.dist-info/LICENSE
torchgel-2.0.0.dist-info/WHEEL
torchgel-2.0.0.dist-info/METADATA
torchgel-2.0.0.dist-info/RECORD
