Metadata-Version: 2.1
Name: torchgel
Version: 2.0.0
Summary: PyTorch implementation of group elastic net
Home-page: https://github.com/jayanthkoushik/torch-gel
License: MIT
Keywords: pytorch,lasso,elasticnet
Author: Jayanth Koushik
Author-email: jnkoushik@gmail.com
Requires-Python: >=3.6.1,<4.0.0
Classifier: Development Status :: 4 - Beta
Classifier: Intended Audience :: Science/Research
Classifier: License :: OSI Approved :: MIT License
Classifier: Natural Language :: English
Classifier: Operating System :: OS Independent
Classifier: Programming Language :: Python :: 3
Classifier: Programming Language :: Python :: 3.7
Classifier: Programming Language :: Python :: 3.8
Classifier: Programming Language :: Python :: 3.9
Classifier: Topic :: Scientific/Engineering :: Mathematics
Provides-Extra: test
Requires-Dist: cvxopt (==1.2.5); extra == "test"
Requires-Dist: cvxpy (>=1.0,<2.0); extra == "test"
Requires-Dist: numpy (>=1.10,<2.0)
Requires-Dist: scipy; extra == "test"
Requires-Dist: tqdm (>=4.0,<5.0)
Project-URL: Repository, https://github.com/jayanthkoushik/torch-gel
